tasktb/__init__.py
tasktb/ctl.py
tasktb/default.py
tasktb/function.py
tasktb/model.py
tasktb/modelmid.py
tasktb/security.py
tasktb/tab.py
tasktb/version.py
tasktb/web.py
tasktb/server/__init__.py
tasktb/server/base.py
tasktb/server/producer.py
tasktb/utils/__init__.py
tasktb-1.0.11.dist-info/LICENSE
tasktb-1.0.11.dist-info/METADATA
tasktb-1.0.11.dist-info/WHEEL
tasktb-1.0.11.dist-info/top_level.txt
tasktb-1.0.11.dist-info/RECORD
