Metadata-Version: 2.1
Name: tasktb
Version: 1.0.11
Summary: TB(terabytes) of task crontab table data manager with web or code easily
Home-page: https://github.com/DJMIN/tasktb
Author: readerror
Author-email: readerror@sina.com
Maintainer: readerror
Maintainer-email: readerror@sina.com
License: GPL License
Platform: all
Requires-Python: >=3.7
License-File: LICENSE
Requires-Dist: fastapi
Requires-Dist: requests
Requires-Dist: uvicorn
Requires-Dist: click
Requires-Dist: sqlalchemy
Requires-Dist: python-multipart
Requires-Dist: wheel
Requires-Dist: twine
Requires-Dist: pycryptodome
Requires-Dist: werkzeug
Requires-Dist: pydantic
Requires-Dist: python-jose
Requires-Dist: guesstime
Requires-Dist: orjson
Requires-Dist: setuptools (==57.5.0)
Requires-Dist: walrus
Requires-Dist: aiomysql
Requires-Dist: async-pool-executor
Requires-Dist: aiosqlite
Requires-Dist: asyncpg
Requires-Dist: greenlet
